flask_flare/__init__.py
flask_flare/extensions.py
flask_flare/flare.py
flask_flare/static/flask_flare.css
flask_flare/static/flask_flare.min.css
flask_flare/static/src/input.css
flask_flare/templates/button.html
flask_flare/templates/select.html
flask_flare-0.1.1.dist-info/METADATA
flask_flare-0.1.1.dist-info/WHEEL
flask_flare-0.1.1.dist-info/licenses/LICENSE
flask_flare-0.1.1.dist-info/RECORD
