Metadata-Version: 2.4
Name: flask-flare
Version: 0.1.1
Summary: Give a little flare to your Flask application with componet-style Jinja Tags
License-File: LICENSE
Author: Drew Butcher
Author-email: drewlbutcher@gmail.com
Requires-Python: >=3.10
Classifier: Programming Language :: Python :: 3
Classifier: Programming Language :: Python :: 3.10
Classifier: Programming Language :: Python :: 3.11
Classifier: Programming Language :: Python :: 3.12
Classifier: Programming Language :: Python :: 3.13
Classifier: Programming Language :: Python :: 3.14
Requires-Dist: flask (>=3.0)
Requires-Dist: jinja2 (>=3.1)
